LICENSE
README.md
setup.py
CVE_2021_40438.egg-info/PKG-INFO
CVE_2021_40438.egg-info/SOURCES.txt
CVE_2021_40438.egg-info/dependency_links.txt
CVE_2021_40438.egg-info/entry_points.txt
CVE_2021_40438.egg-info/requires.txt
CVE_2021_40438.egg-info/top_level.txt
cve202140438/__init__.py
cve202140438/main.py
cve202140438/includes/__init__.py
cve202140438/includes/bot.py
cve202140438/includes/filereader.py
cve202140438/includes/scan.py
cve202140438/includes/writefile.py
cve202140438/utils/__init__.py
cve202140438/utils/configure.py
cve202140438/utils/const.py
cve202140438/utils/helpers.py
cve202140438/utils/status.py